SurrealGAN/Surreal_GAN_representation_learning.py
SurrealGAN/__init__.py
SurrealGAN/data_loading.py
SurrealGAN/model.py
SurrealGAN/modules.py
SurrealGAN/networks.py
SurrealGAN/training.py
SurrealGAN/utils.py
SurrealGAN-0.0.2.dist-info/METADATA
SurrealGAN-0.0.2.dist-info/WHEEL
SurrealGAN-0.0.2.dist-info/top_level.txt
SurrealGAN-0.0.2.dist-info/RECORD
