Metadata-Version: 2.1
Name: SurrealGAN
Version: 0.0.2
Summary: A python implementation of Surreal-GAN for semisupervised representation learning
Home-page: https://github.com/zhijian-yang/SurrealGAN
Author: zhijian.yang
Author-email: zhijianyang@outlook.com
License: UNKNOWN
Platform: UNKNOWN
Classifier: Programming Language :: Python :: 3
Classifier: License :: OSI Approved :: MIT License
Classifier: Operating System :: OS Independent
Requires-Dist: numpy (>=1.22.3)
Requires-Dist: tqdm (>=4.50.2)
Requires-Dist: torch (>=1.10.2)
Requires-Dist: scikit-learn (>=0.24.2)
Requires-Dist: scipy (>=1.8.0)
Requires-Dist: pandas (>=1.4.2)
Requires-Dist: lifelines (>=0.26.3)
